opendapi/__init__.py
opendapi/adapters/__init__.py
opendapi/adapters/dapi_server.py
opendapi/adapters/file.py
opendapi/adapters/git.py
opendapi/cli/__init__.py
opendapi/cli/common.py
opendapi/cli/context_agnostic.py
opendapi/cli/init.py
opendapi/cli/main.py
opendapi/cli/onboarding/__init__.py
opendapi/cli/onboarding/opendapi_config/__init__.py
opendapi/cli/onboarding/opendapi_config/base.py
opendapi/cli/onboarding/opendapi_config/defs.py
opendapi/cli/onboarding/opendapi_config/orms/__init__.py
opendapi/cli/onboarding/opendapi_config/orms/activerecord.py
opendapi/cli/onboarding/opendapi_config/orms/pynamodb.py
opendapi/cli/options.py
opendapi/cli/repos/__init__.py
opendapi/cli/repos/github/__init__.py
opendapi/cli/repos/github/main.py
opendapi/cli/repos/github/options.py
opendapi/cli/repos/github/runners/__init__.py
opendapi/cli/repos/github/runners/buildkite/__init__.py
opendapi/cli/repos/github/runners/buildkite/base_collect.py
opendapi/cli/repos/github/runners/buildkite/head_collect.py
opendapi/cli/repos/github/runners/buildkite/head_collect_server_upload.py
opendapi/cli/repos/github/runners/buildkite/head_collect_server_upload_start_cicd.py
opendapi/cli/repos/github/runners/buildkite/init_cicd.py
opendapi/cli/repos/github/runners/buildkite/main.py
opendapi/cli/repos/github/runners/buildkite/options.py
opendapi/cli/repos/github/runners/buildkite/run.py
opendapi/cli/repos/github/runners/buildkite/server_sync.py
opendapi/cli/repos/github/runners/buildkite/server_upload.py
opendapi/cli/repos/github/runners/buildkite/server_upload_start_cicd.py
opendapi/cli/repos/github/runners/buildkite/start_cicd.py
opendapi/cli/repos/github/runners/github/__init__.py
opendapi/cli/repos/github/runners/github/base_collect.py
opendapi/cli/repos/github/runners/github/head_collect.py
opendapi/cli/repos/github/runners/github/head_collect_server_upload.py
opendapi/cli/repos/github/runners/github/head_collect_server_upload_start_cicd.py
opendapi-1.0.95.dist-info/METADATA
opendapi-1.0.95.dist-info/WHEEL
opendapi-1.0.95.dist-info/entry_points.txt
opendapi-1.0.95.dist-info/licenses/LICENSE
opendapi-1.0.95.dist-info/RECORD
