Metadata-Version: 2.4
Name: opendapi
Version: 1.0.95
Summary: Python client for Open DAPI interfaces
License: Apache-2.0
License-File: LICENSE
Author: Woven
Author-email: opendapi-publisher@woven.dev
Requires-Python: >=3.9,<4.0
Classifier: License :: OSI Approved :: Apache Software License
Classifier: Programming Language :: Python :: 3
Classifier: Programming Language :: Python :: 3.9
Classifier: Programming Language :: Python :: 3.10
Classifier: Programming Language :: Python :: 3.11
Classifier: Programming Language :: Python :: 3.12
Classifier: Programming Language :: Python :: 3.13
Classifier: Programming Language :: Python :: 3.14
Requires-Dist: aiohttp (>=3.12.12,<4.0.0)
Requires-Dist: click (>=8.0.0,<9.0.0)
Requires-Dist: deepmerge (>=1.1.0,<2.0.0)
Requires-Dist: esprima (>=4.0.1,<5.0.0)
Requires-Dist: grpcio-tools (>=1.73.0,<2.0.0)
Requires-Dist: jinja2 (>=3.1.6,<4.0.0)
Requires-Dist: jsonref (>=1.1.0,<2.0.0)
Requires-Dist: jsonschema (>=4.17.3,<5.0.0)
Requires-Dist: jsonschema-rs (>=0.30.0,<0.31.0)
Requires-Dist: pyparsing (>=3.0.0,<4.0.0)
Requires-Dist: requests (>=2.32.4,<3.0.0)
Requires-Dist: requests-cache (>=1.2.0,<2.0.0)
Requires-Dist: rich (>=14.2.0,<15.0.0)
Requires-Dist: ruamel-yaml (>=0.17.32,<0.18.0)
Requires-Dist: sentry-sdk (>=2.41.0,<3.0.0)
Requires-Dist: sqlglot[rs] (>=27.6.0,<28.0.0)
Project-URL: Homepage, https://woven.dev
Project-URL: Quickstart, https://opendapi.org
